climateservaccess/__init__.py
climateservaccess/climateservaccess.py
climateservaccess-1.0.4.dist-info/METADATA
climateservaccess-1.0.4.dist-info/WHEEL
climateservaccess-1.0.4.dist-info/top_level.txt
climateservaccess-1.0.4.dist-info/RECORD
