Metadata-Version: 2.1
Name: climateservaccess
Version: 1.0.4
Summary: A custom library for accessing the ClimateSERV API
Home-page: https://github.com/adamzhen/climateservAccess
Author: Adam Zheng
Author-email: Adam Zheng <adzheng@tamu.edu>
Project-URL: Homepage, https://github.com/adamzhen/climateservAccess
Project-URL: Issues, https://github.com/adamzhen/climateservAccess/issues
Classifier: Programming Language :: Python :: 3
Classifier: License :: OSI Approved :: MIT License
Classifier: Operating System :: OS Independent
Requires-Python: >=3.7
